hashtbl/__init__.py
hashtbl-1.0.5.dist-info/LICENSE
hashtbl-1.0.5.dist-info/METADATA
hashtbl-1.0.5.dist-info/WHEEL
hashtbl-1.0.5.dist-info/top_level.txt
hashtbl-1.0.5.dist-info/RECORD
