Metadata-Version: 2.1
Name: hashtbl
Version: 1.0.5
Summary: Sophisticate Hash Table
Home-page: https://pypi.org/project/hashtbl/
Author: khiat Mohammed Abderrezzak
Author-email: khiat.dev@gmail.com
License: MIT
Keywords: hash table
Classifier: Programming Language :: Python :: 3
Classifier: Operating System :: OS Independent
Classifier: License :: OSI Approved :: MIT License
Requires-Python: >=3.6
License-File: LICENSE
Requires-Dist: linkedit (>=1.1.3)
